pycoolmaster/__init__.py
pycoolmaster-0.2.3.dist-info/LICENSE
pycoolmaster-0.2.3.dist-info/METADATA
pycoolmaster-0.2.3.dist-info/WHEEL
pycoolmaster-0.2.3.dist-info/top_level.txt
pycoolmaster-0.2.3.dist-info/zip-safe
pycoolmaster-0.2.3.dist-info/RECORD
