Metadata-Version: 2.1
Name: pycoolmaster
Version: 0.2.3
Summary: Lightweight Python API for older (RS232-only) CoolMaster HVAC bridges
Home-page: http://github.com/issacg/pycoolmaster
Author: Issac Goldstand
Author-email: margol@beamartyr.net
License: UNKNOWN
Keywords: hvac homeautomation
Platform: UNKNOWN
Classifier: Development Status :: 3 - Alpha
Classifier: License :: OSI Approved :: Apache Software License
Classifier: Operating System :: OS Independent
Classifier: Programming Language :: Python :: 3.5
Classifier: Topic :: Home Automation
Classifier: Topic :: Software Development :: Libraries :: Python Modules
Requires-Dist: pyserial
